covet/__init__.py
covet/cli.py
covet/config.py
covet/database.py
covet/py.typed
covet/rate_limiting.py
covet/rust_core.py
covet/validation.py
covet/websocket.py
covet/_rust/__init__.py
covet/api/__init__.py
covet/api/graphql.py
covet/api/versioning.py
covet/api/docs/__init__.py
covet/api/docs/example_generator.py
covet/api/docs/markdown_generator.py
covet/api/docs/openapi_generator.py
covet/api/docs/postman_collection.py
covet/api/docs/redoc_ui.py
covet/api/docs/swagger_ui.py
covet/api/graphql/__init__.py
covet/api/graphql/authentication.py
covet/api/graphql/dataloader.py
covet/api/graphql/errors.py
covet/api/graphql/execution.py
covet/api/graphql/framework.py
covet/api/graphql/introspection.py
covet/api/graphql/lexer.py
covet/api/graphql/middleware.py
covet/api/graphql/pagination.py
covet/api/graphql/parser.py
covet/api/graphql/playground.py
covet/api/graphql/query_complexity.py
covet/api/graphql/resolvers.py
covet/api/graphql/schema.py
covet/api/graphql/schema_builder.py
covet/api/graphql/subscriptions.py
covet/api/graphql/type_system.py
covet/api/graphql/upload.py
covet/api/graphql/validation.py
covet/api/graphql/websocket_protocol.py
covet/api/rest/__init__.py
covet/api/rest/app.py
covet/api/rest/auth.py
covet/api/rest/crud_generator.py
covet/api/rest/errors.py
covet/api/rest/filtering.py
covet/api/rest/framework.py
covet/api/rest/middleware.py
covet/api/rest/openapi.py
covet/api/rest/pagination.py
covet/api/rest/ratelimit.py
covet/api/rest/router.py
covet/api/rest/serialization.py
covet/api/rest/sorting.py
covet/api/rest/validation.py
covet/api/rest/versioning.py
covet/api/rest/routers/__init__.py
covet/api/rest/routers/health.py
covet/api/schemas/__init__.py
covet/api/schemas/base.py
covet/api/schemas/models.py
covet/api/schemas/requests.py
covet/api/schemas/responses.py
covet/api/utils/__init__.py
covet/api/utils/json_utils.py
covet/api/versioning/__init__.py
covet/api/versioning/compatibility.py
covet/api/versioning/deprecation.py
covet-0.1.0b5.dist-info/licenses/LICENSE
covet-0.1.0b5.dist-info/licenses/LICENSE_HEADER
covet-0.1.0b5.dist-info/METADATA
covet-0.1.0b5.dist-info/WHEEL
covet-0.1.0b5.dist-info/entry_points.txt
covet-0.1.0b5.dist-info/top_level.txt
covet-0.1.0b5.dist-info/RECORD
