Metadata-Version: 2.4
Name: covet
Version: 0.1.0b5
Summary: A high-performance Python web framework with Rust-optimized components for modern async applications
Author: Vipin Kumar
Maintainer: Vipin Kumar
License: Proprietary
Project-URL: Author, https://github.com/vipin08
Project-URL: Documentation, https://github.com/vipin08/Covet-doc
Keywords: rest-api,http,api,python-rust,async,asgi,web-framework,graphql,websocket,high-performance,rust-extensions,orm,database,jwt-auth
Classifier: Development Status :: 4 - Beta
Classifier: Environment :: Web Environment
Classifier: Framework :: AsyncIO
Classifier: Intended Audience :: Developers
Classifier: License :: Other/Proprietary License
Classifier: Natural Language :: English
Classifier: Operating System :: OS Independent
Classifier: Programming Language :: Python :: 3
Classifier: Programming Language :: Python :: 3.9
Classifier: Programming Language :: Python :: 3.10
Classifier: Programming Language :: Python :: 3.11
Classifier: Programming Language :: Python :: 3.12
Classifier: Programming Language :: Python :: 3 :: Only
Classifier: Programming Language :: Python :: Implementation :: CPython
Classifier: Programming Language :: Rust
Classifier: Topic :: Internet :: WWW/HTTP
Classifier: Topic :: Internet :: WWW/HTTP :: HTTP Servers
Classifier: Topic :: Software Development :: Libraries :: Application Frameworks
Classifier: Topic :: Software Development :: Libraries :: Python Modules
Classifier: Typing :: Typed
Requires-Python: >=3.9
License-File: LICENSE
License-File: LICENSE_HEADER
Requires-Dist: pydantic>=2.12.0
Requires-Dist: prometheus-client>=0.23.1
Requires-Dist: psutil>=7.1.0
Requires-Dist: PyJWT>=2.8.0
Requires-Dist: uvicorn[standard]>=0.37.0
Provides-Extra: dev
Requires-Dist: pytest>=8.4.2; extra == "dev"
Requires-Dist: pytest-asyncio>=1.2.0; extra == "dev"
Requires-Dist: pytest-cov>=7.0.0; extra == "dev"
Requires-Dist: pytest-mock>=3.15.1; extra == "dev"
Requires-Dist: pytest-benchmark>=5.1.0; extra == "dev"
Requires-Dist: black>=25.9.0; extra == "dev"
Requires-Dist: ruff>=0.14.0; extra == "dev"
Requires-Dist: mypy>=1.7.1; extra == "dev"
Requires-Dist: pre-commit>=3.5.0; extra == "dev"
Requires-Dist: httpx>=0.28.1; extra == "dev"
Requires-Dist: maturin>=1.9.4; extra == "dev"
Provides-Extra: docs
Requires-Dist: mkdocs>=1.5.3; extra == "docs"
Requires-Dist: mkdocs-material>=9.5.32; extra == "docs"
Requires-Dist: mkdocstrings[python]>=0.24.0; extra == "docs"
Provides-Extra: test
Requires-Dist: pytest>=8.4.2; extra == "test"
Requires-Dist: pytest-asyncio>=1.2.0; extra == "test"
Requires-Dist: pytest-cov>=7.0.0; extra == "test"
Requires-Dist: pytest-mock>=3.15.1; extra == "test"
Requires-Dist: pytest-benchmark>=5.1.0; extra == "test"
Requires-Dist: httpx>=0.28.1; extra == "test"
Provides-Extra: security
Requires-Dist: pyotp>=2.9.0; extra == "security"
Requires-Dist: passlib[bcrypt]>=1.7.4; extra == "security"
Requires-Dist: validators>=0.22.0; extra == "security"
Requires-Dist: bleach>=6.2.0; extra == "security"
Requires-Dist: limits>=3.7.0; extra == "security"
Requires-Dist: python-multipart>=0.0.6; extra == "security"
Requires-Dist: email-validator>=2.1.0; extra == "security"
Provides-Extra: web
Requires-Dist: uvicorn[standard]>=0.37.0; extra == "web"
Requires-Dist: pydantic>=2.12.0; extra == "web"
Requires-Dist: pydantic-settings>=2.11.0; extra == "web"
Provides-Extra: database
Requires-Dist: sqlalchemy>=2.0.43; extra == "database"
Requires-Dist: alembic>=1.16.5; extra == "database"
Requires-Dist: asyncpg>=0.30.0; extra == "database"
Requires-Dist: aiomysql>=0.2.0; extra == "database"
Provides-Extra: production
Requires-Dist: uvicorn[standard]>=0.37.0; extra == "production"
Requires-Dist: asyncpg>=0.30.0; extra == "production"
Requires-Dist: aiomysql>=0.2.0; extra == "production"
Requires-Dist: redis>=6.4.0; extra == "production"
Requires-Dist: aiomemcache>=0.8.0; extra == "production"
Requires-Dist: passlib[bcrypt]>=1.7.4; extra == "production"
Requires-Dist: python-dotenv>=1.1.1; extra == "production"
Provides-Extra: graphql
Requires-Dist: strawberry-graphql>=0.209.0; extra == "graphql"
Provides-Extra: orm
Requires-Dist: sqlalchemy>=2.0.43; extra == "orm"
Requires-Dist: alembic>=1.16.5; extra == "orm"
Provides-Extra: rust
Requires-Dist: maturin>=1.9.4; extra == "rust"
Provides-Extra: monitoring
Requires-Dist: opentelemetry-api>=1.21.0; extra == "monitoring"
Requires-Dist: opentelemetry-sdk>=1.21.0; extra == "monitoring"
Requires-Dist: structlog>=23.2.0; extra == "monitoring"
Provides-Extra: full
Requires-Dist: uvicorn[standard]>=0.37.0; extra == "full"
Requires-Dist: pydantic>=2.12.0; extra == "full"
Requires-Dist: pydantic-settings>=2.11.0; extra == "full"
Requires-Dist: httpx>=0.28.1; extra == "full"
Requires-Dist: sqlalchemy>=2.0.43; extra == "full"
Requires-Dist: alembic>=1.16.5; extra == "full"
Requires-Dist: asyncpg>=0.30.0; extra == "full"
Requires-Dist: aiomysql>=0.2.0; extra == "full"
Requires-Dist: redis>=6.4.0; extra == "full"
Requires-Dist: aiomemcache>=0.8.0; extra == "full"
Requires-Dist: strawberry-graphql>=0.283.2; extra == "full"
Requires-Dist: passlib[bcrypt]>=1.7.4; extra == "full"
Requires-Dist: validators>=0.22.0; extra == "full"
Requires-Dist: bleach>=6.2.0; extra == "full"
Requires-Dist: limits>=5.5.0; extra == "full"
Requires-Dist: python-multipart>=0.0.20; extra == "full"
Requires-Dist: email-validator>=2.3.0; extra == "full"
Requires-Dist: click>=8.3.0; extra == "full"
Requires-Dist: rich>=14.2.0; extra == "full"
Requires-Dist: prometheus-client>=0.23.1; extra == "full"
Requires-Dist: opentelemetry-api>=1.37.0; extra == "full"
Requires-Dist: opentelemetry-sdk>=1.37.0; extra == "full"
Requires-Dist: structlog>=25.4.0; extra == "full"
Requires-Dist: python-dotenv>=1.1.1; extra == "full"
Requires-Dist: pyyaml>=6.0.3; extra == "full"
Requires-Dist: jinja2>=3.1.6; extra == "full"
Requires-Dist: maturin>=1.9.4; extra == "full"
Dynamic: license-file
